animplotlib/__init__.py
animplotlib/__init__.pyi
animplotlib/animplot.py
animplotlib/animplot.pyi
animplotlib/animplot3d.py
animplotlib/animplot3d.pyi
animplotlib/py.typed
animplotlib-0.2.6.dist-info/licenses/LICENSE
animplotlib-0.2.6.dist-info/METADATA
animplotlib-0.2.6.dist-info/WHEEL
animplotlib-0.2.6.dist-info/top_level.txt
animplotlib-0.2.6.dist-info/RECORD
