Metadata-Version: 2.4
Name: animplotlib
Version: 0.2.6
Summary: A thin wrapper around the matplotlib FuncAnimation class
Home-page: https://github.com/aymenhafeez/animplotlib/
Author: Aymen Hafeez
Author-email: aymennh@gmail.com
License: MIT
Requires-Python: >=3.7
License-File: LICENSE
Requires-Dist: matplotlib>=1.1
Dynamic: author
Dynamic: author-email
Dynamic: description
Dynamic: description-content-type
Dynamic: home-page
Dynamic: license
Dynamic: license-file
Dynamic: requires-dist
Dynamic: requires-python
Dynamic: summary
